scikit_na/__init__.py
scikit_na/_export.py
scikit_na/_report.py
scikit_na/_stats.py
scikit_na/altair/__init__.py
scikit_na/altair/_altair.py
scikit_na/mpl/__init__.py
scikit_na/mpl/_mpl.py
scikit_na-0.3.0.dist-info/licenses/LICENSE
scikit_na-0.3.0.dist-info/METADATA
scikit_na-0.3.0.dist-info/WHEEL
scikit_na-0.3.0.dist-info/top_level.txt
scikit_na-0.3.0.dist-info/RECORD
