Metadata-Version: 2.4
Name: scikit-na
Version: 0.3.0
Summary: Missing Values Analysis for Data Science
Author-email: Maksim Terpilovskii <maximtrp@gmail.com>
License: MIT License
Project-URL: homepage, https://github.com/maximtrp/scikit-na
Project-URL: documentation, https://scikit-na.readthedocs.io/
Keywords: data science,data analytics,statistics
Classifier: License :: OSI Approved :: MIT License
Classifier: Operating System :: OS Independent
Classifier: Programming Language :: Python :: 3.9
Classifier: Programming Language :: Python :: 3.10
Classifier: Programming Language :: Python :: 3.11
Classifier: Programming Language :: Python :: 3.12
Classifier: Programming Language :: Python :: 3.13
Classifier: Topic :: Scientific/Engineering :: Information Analysis
Classifier: Topic :: Text Processing :: General
Requires-Python: >=3.9
License-File: LICENSE
Requires-Dist: numpy>=1.21.0
Requires-Dist: pandas>=1.3.0
Requires-Dist: statsmodels>=0.12.0
Requires-Dist: matplotlib>=3.5.0
Requires-Dist: seaborn>=0.11.0
Requires-Dist: altair>=5.0.0
Requires-Dist: ipywidgets>=7.6.0
Provides-Extra: test
Requires-Dist: pytest>=6.0; extra == "test"
Requires-Dist: codecov>=2.1.0; extra == "test"
Requires-Dist: coverage>=5.5; extra == "test"
Provides-Extra: export
Requires-Dist: openpyxl>=3.0.0; extra == "export"
Requires-Dist: xlsxwriter>=1.4.0; extra == "export"
Provides-Extra: dev
Requires-Dist: black>=22.0; extra == "dev"
Requires-Dist: flake8>=4.0; extra == "dev"
Requires-Dist: mypy>=0.900; extra == "dev"
Requires-Dist: pre-commit>=2.15; extra == "dev"
Provides-Extra: all
Requires-Dist: scikit-na[dev,export,test]; extra == "all"
Dynamic: license-file
